[
    {"_id": 5b041ea97fc91d4320f90139, "firstName": "101", "lastName": "Fight Club", "email": "1999", "company": "8.1", "phone":123456},
    {"_id": 5b041ea97fc91d4320f90138, "firstName": "102", "lastName": "Fight Club", "email": "1999", "company": "8.1", "phone":123456},
    {"_id": 5b041ea97fc91d4320f90137, "firstName": "103", "lastName": "Fight Club", "email": "1999", "company": "8.1", "phone":123456},
    {"_id": 5b041ea97fc91d4320f90136, "firstName": "104", "lastName": "Fight Club", "email": "1999", "company": "8.1", "phone":123456}
]